setup.py
bt_ctfirtg.egg-info/PKG-INFO
bt_ctfirtg.egg-info/SOURCES.txt
bt_ctfirtg.egg-info/dependency_links.txt
bt_ctfirtg.egg-info/entry_points.txt
bt_ctfirtg.egg-info/requires.txt
bt_ctfirtg.egg-info/top_level.txt
btctfirtg/__init__.py
btctfirtg/cli.py
btctfirtg/codegen.py
btctfirtg/config.py
btctfirtg/gen.py
btctfirtg/metadata.py