Metadata-Version: 1.0
Name: bt-ctfirtg
Version: 0.0.1
Summary: Generator of Babeltrace CTF IR field type creation code
Home-page: https://github.com/eepp/bt-ctfirtg
Author: Philippe Proulx
Author-email: eeppeliteloop@gmail.com
License: MIT
Keywords: ctf ctf-ir bt babeltrace
Platform: UNKNOWN
